{
    "actorSpecification": 1,
    "name": "meta-ads-scraper",
    "title": "Meta Ads Library Web Scraper",
    "description": "Scraper per la Meta Ads Library che utilizza web scraping per estrarre dati pubblicitari pubblici senza necessità di token di accesso o verifiche aziendali. Supporta ricerca avanzata, filtri per paese e tipo, scroll automatico e gestione cookie.",
    "version": "0.0.1",
    "storages": {
        "dataset": {
            "actorSpecification": 1,
            "title": "Meta Ads Scraper Results",
            "views": {
                "default": {
                    "title": "Default View",
                    "transformation": {
                        "fields": [
                            "ad_id",
                            "page_name",
                            "ad_creative_body",
                            "ad_creative_link_caption",
                            "ad_creative_link_description",
                            "ad_creative_link_title",
                            "ad_delivery_start_time",
                            "ad_delivery_stop_time",
                            "ad_snapshot_url",
                            "currency",
                            "demographic_distribution",
                            "funding_entity",
                            "impressions",
                            "spend",
                            "page_id",
                            "publisher_platforms"
                        ]
                    },
                    "display": {
                        "component": "table"
                    }
                }
            }
        }
    },
    "dockerfile": "./Dockerfile"
}